{
  "hash": "296513e0",
  "configHash": "3b3196ca",
  "lockfileHash": "586f7402",
  "browserHash": "c9c0a9a2",
  "optimized": {
    "lucide-react": {
      "src": "../../node_modules/lucide-react/dist/esm/lucide-react.js",
      "file": "lucide-react.js",
      "fileHash": "af9d7bab",
      "needsInterop": false
    },
    "react": {
      "src": "../../node_modules/react/index.js",
      "file": "react.js",
      "fileHash": "266a1597",
      "needsInterop": true
    },
    "react-dom/client": {
      "src": "../../node_modules/react-dom/client.js",
      "file": "react-dom_client.js",
      "fileHash": "df8bbd7f",
      "needsInterop": true
    },
    "react-router-dom": {
      "src": "../../node_modules/react-router-dom/dist/index.mjs",
      "file": "react-router-dom.js",
      "fileHash": "d09965ff",
      "needsInterop": false
    }
  },
  "chunks": {
    "chunk-K35MWTXD": {
      "file": "chunk-K35MWTXD.js"
    },
    "chunk-ZZLEEZYP": {
      "file": "chunk-ZZLEEZYP.js"
    }
  }
}